sbc/__init__.py
sbc/cli.py
sbc/config.py
sbc/magic.py
sbc/pdf.py
sbc/preprocessors.py
sbc/search.py
sbc/utils.py
sbc/leaderboard/__init__.py
sbc/leaderboard/client.py
sbc/leaderboard/server/__init__.py
sbc/leaderboard/server/bot.py
sbc/leaderboard/server/database.py
sbc/persistence/__init__.py
sbc/persistence/storage.py
sbc/themes/__init__.py
sbc/widgets/__init__.py
sbc/widgets/base.py
sbc/widgets/flashcards.py
sbc/widgets/puzzles.py
sbc/widgets/quiz.py
sbc/widgets/reflection.py
sbc/widgets/trivia.py
sbcourse-0.1.7.dist-info/METADATA
sbcourse-0.1.7.dist-info/WHEEL
sbcourse-0.1.7.dist-info/entry_points.txt
sbcourse-0.1.7.dist-info/licenses/LICENSE
sbcourse-0.1.7.dist-info/RECORD
