Metadata-Version: 2.4
Name: sbcourse
Version: 0.1.7
Summary: Steel Bank Course - A comprehensive toolkit for managing Jupyter notebook-based courses with interactive widgets, leaderboards, and gamification
Project-URL: Homepage, https://github.com/jkitchin/sbcourse
Project-URL: Documentation, https://github.com/jkitchin/sbcourse#readme
Project-URL: Repository, https://github.com/jkitchin/sbcourse
Project-URL: Issues, https://github.com/jkitchin/sbcourse/issues
Author-email: John Kitchin <jkitchin@andrew.cmu.edu>
License: MIT
License-File: LICENSE
Keywords: course,education,flashcards,jupyter,leaderboard,quiz,widgets
Classifier: Development Status :: 3 - Alpha
Classifier: Framework :: Jupyter
Classifier: Intended Audience :: Education
Classifier: Intended Audience :: Science/Research
Classifier: License :: OSI Approved :: MIT License
Classifier: Operating System :: OS Independent
Classifier: Programming Language :: Python :: 3
Classifier: Programming Language :: Python :: 3.10
Classifier: Programming Language :: Python :: 3.11
Classifier: Programming Language :: Python :: 3.12
Classifier: Topic :: Education
Requires-Python: >=3.10
Requires-Dist: chromadb
Requires-Dist: click
Requires-Dist: ipykernel
Requires-Dist: ipython
Requires-Dist: ipywidgets>=8.0.0
Requires-Dist: jupyter-server
Requires-Dist: nbconvert
Requires-Dist: nbformat
Requires-Dist: playwright
Requires-Dist: pypdf>=4.0.0
Requires-Dist: pyyaml>=6.0
Requires-Dist: requests
Requires-Dist: tomli>=2.0.0; python_version < '3.11'
Requires-Dist: tqdm
Provides-Extra: bot
Requires-Dist: discord-py>=2.3.0; extra == 'bot'
Requires-Dist: flask>=3.0.0; extra == 'bot'
Requires-Dist: python-dotenv>=1.0.0; extra == 'bot'
Provides-Extra: dev
Requires-Dist: pytest-cov>=4.0.0; extra == 'dev'
Requires-Dist: pytest>=7.0.0; extra == 'dev'
Requires-Dist: ruff>=0.1.0; extra == 'dev'
